cythonbiogeme/__init__.py
cythonbiogeme/cythonbiogeme.cp311-win_amd64.pyd
cythonbiogeme/version.py
cythonbiogeme/cpp/READ.ME
cythonbiogeme/cpp/__init__.py
cythonbiogeme/cpp/bioCfsqp.cc
cythonbiogeme/cpp/bioCfsqp.h
cythonbiogeme/cpp/bioConst.h
cythonbiogeme/cpp/bioConstants.h
cythonbiogeme/cpp/bioDebug.h
cythonbiogeme/cpp/bioDerivatives.cc
cythonbiogeme/cpp/bioDerivatives.h
cythonbiogeme/cpp/bioExceptions.cc
cythonbiogeme/cpp/bioExceptions.h
cythonbiogeme/cpp/bioExprAnd.cc
cythonbiogeme/cpp/bioExprAnd.h
cythonbiogeme/cpp/bioExprBelongsTo.cc
cythonbiogeme/cpp/bioExprBelongsTo.h
cythonbiogeme/cpp/bioExprConditionalSum.cc
cythonbiogeme/cpp/bioExprConditionalSum.h
cythonbiogeme/cpp/bioExprCos.cc
cythonbiogeme/cpp/bioExprCos.h
cythonbiogeme/cpp/bioExprDerive.cc
cythonbiogeme/cpp/bioExprDerive.h
cythonbiogeme/cpp/bioExprDivide.cc
cythonbiogeme/cpp/bioExprDivide.h
cythonbiogeme/cpp/bioExprDraws.cc
cythonbiogeme/cpp/bioExprDraws.h
cythonbiogeme/cpp/bioExprElem.cc
cythonbiogeme/cpp/bioExprElem.h
cythonbiogeme/cpp/bioExprEqual.cc
cythonbiogeme/cpp/bioExprEqual.h
cythonbiogeme/cpp/bioExprExp.cc
cythonbiogeme/cpp/bioExprExp.h
cythonbiogeme/cpp/bioExprFixedParameter.cc
cythonbiogeme/cpp/bioExprFixedParameter.h
cythonbiogeme/cpp/bioExprFreeParameter.cc
cythonbiogeme/cpp/bioExprFreeParameter.h
cythonbiogeme/cpp/bioExprGaussHermite.cc
cythonbiogeme/cpp/bioExprGaussHermite.h
cythonbiogeme/cpp/bioExprGreater.cc
cythonbiogeme/cpp/bioExprGreater.h
cythonbiogeme/cpp/bioExprGreaterOrEqual.cc
cythonbiogeme/cpp/bioExprGreaterOrEqual.h
cythonbiogeme/cpp/bioExprIntegrate.cc
cythonbiogeme/cpp/bioExprIntegrate.h
cythonbiogeme/cpp/bioExprLess.cc
cythonbiogeme/cpp/bioExprLess.h
cythonbiogeme/cpp/bioExprLessOrEqual.cc
cythonbiogeme/cpp/bioExprLessOrEqual.h
cythonbiogeme/cpp/bioExprLinearUtility.cc
cythonbiogeme/cpp/bioExprLinearUtility.h
cythonbiogeme/cpp/bioExprLiteral.cc
cythonbiogeme/cpp/bioExprLiteral.h
cythonbiogeme/cpp/bioExprLiteral_current.cc
cythonbiogeme/cpp/bioExprLog.cc
cythonbiogeme-1.0.4.dist-info/LICENSE
cythonbiogeme-1.0.4.dist-info/METADATA
cythonbiogeme-1.0.4.dist-info/WHEEL
cythonbiogeme-1.0.4.dist-info/top_level.txt
cythonbiogeme-1.0.4.dist-info/RECORD
